{"cameraMode":{"drawMode":0,"name":"Shaded","section":"Shading Mode"},"sceneLighting":false,"audioPlay":false,"sceneViewState":{"showFog":true,"showMaterialUpdate":false,"showSkybox":false,"showFlares":true,"showImageEffects":true,"showParticleSystems":true,"showVisualEffectGraphs":true,"m_FxEnabled":true},"in2DMode":false,"pivot":{"x":-11.5,"y":4.929999828338623,"z":0.0},"rotation":{"x":0.37276482582092287,"y":0.1751750409603119,"z":-0.0718832015991211,"w":0.9084029793739319},"size":6.025211811065674,"orthographic":true}